sciviz/__init__.py
sciviz/src/__init__.py
sciviz/src/sciviz.py
sciviz-0.1.1.dist-info/LICENSE.txt
sciviz-0.1.1.dist-info/METADATA
sciviz-0.1.1.dist-info/WHEEL
sciviz-0.1.1.dist-info/top_level.txt
sciviz-0.1.1.dist-info/RECORD
