Metadata-Version: 2.1
Name: sciviz
Version: 0.1.1
Summary: A package to simplify scientific visualization
Home-page: https://github.com/kantonopoulos/SciViz
Author: Konstantinos Antonopoulos
Author-email: k.antono@outlook.com
License: MIT
Classifier: Intended Audience :: Science/Research
Classifier: License :: OSI Approved :: MIT License
Classifier: Programming Language :: Python :: 3.10
Classifier: Topic :: Scientific/Engineering
Requires-Python: >=3.10
License-File: LICENSE.txt
Provides-Extra: dev
Requires-Dist: unittest ; extra == 'dev'
